drift_client/__init__.py
drift_client/drift_client.py
drift_client/drift_data_package.py
drift_client/error.py
drift_client/influxdb_client.py
drift_client/minio_client.py
drift_client/mqtt_client.py
drift_client/reduct_client.py
drift_python_client-0.10.0.dist-info/LICENSE
drift_python_client-0.10.0.dist-info/METADATA
drift_python_client-0.10.0.dist-info/WHEEL
drift_python_client-0.10.0.dist-info/top_level.txt
drift_python_client-0.10.0.dist-info/RECORD
