Metadata-Version: 2.1
Name: drift-python-client
Version: 0.10.0
Summary: Python Client to access data of PANDA|Drift
Author-email: "PANDA, GmbH" <info@panda.technology>
Maintainer-email: "PANDA, GmbH" <info@panda.technology>
License: Mozilla Public License Version 2.0
Project-URL: Homepage, https://driftpythonclient.readthedocs.io/en/latest/
Project-URL: Documentation, https://driftpythonclient.readthedocs.io/en/latest/
Project-URL: Source, https://github.com/panda-official/DriftPythonClient
Project-URL: Changelog, https://github.com/panda-official/DriftPythonClient/blob/develop/CHANGELOG.md
Keywords: drift,api,edge-computing,data,cli
Classifier: Development Status :: 4 - Beta
Classifier: Programming Language :: Python :: 3 :: Only
Classifier: Intended Audience :: Developers
Classifier: Intended Audience :: Information Technology
Classifier: Operating System :: OS Independent
Classifier: Topic :: Software Development :: Libraries :: Python Modules
Classifier: Topic :: Software Development :: Libraries
Classifier: License :: OSI Approved :: Mozilla Public License 2.0 (MPL 2.0)
Requires-Python: >=3.8
License-File: LICENSE
Requires-Dist: influxdb-client <2.0.0,>=1.36.1
Requires-Dist: drift-protocol <1.0.0,>=0.6.0
Requires-Dist: wavelet-buffer <1.0.0,>=0.7.0
Requires-Dist: drift-bytes <1.0.0,>=0.2.0
Requires-Dist: paho-mqtt <2.0.0,>=1.6.1
Requires-Dist: numpy <2.0.0,>=1.24.3
Requires-Dist: deprecation ==2.1.0
Requires-Dist: reduct-py <2.0.0,>=1.6
Requires-Dist: minio ==7.1.10
Provides-Extra: docs
Requires-Dist: mkdocs <2.0.0,>=1.4.3 ; extra == 'docs'
Requires-Dist: mkdocs-material <10.0.0,>=9.1.16 ; extra == 'docs'
Requires-Dist: plantuml-markdown <4.0.0,>=3.9.1 ; extra == 'docs'
Requires-Dist: mkdocstrings[python] ~=0.22 ; extra == 'docs'
Requires-Dist: mkdocs-jupyter ~=0.24 ; extra == 'docs'
Provides-Extra: format
Requires-Dist: black[jypyter] >=23.3.0 ; extra == 'format'
Provides-Extra: lint
Requires-Dist: pylint <3.0.0,>=2.17.4 ; extra == 'lint'
Requires-Dist: pylint-protobuf <1.0.0,>=0.20.2 ; extra == 'lint'
Provides-Extra: test
Requires-Dist: pytest <8.0.0,>=7.3.2 ; extra == 'test'
Requires-Dist: pytest-mock <4.0.0,>=3.11 ; extra == 'test'
